check_ip/__init__.py
check_ip/cli.py
check_ip/config.py
check_ip/api/__init__.py
check_ip/api/cloudflare.py
check_ip-0.4.5.dist-info/LICENSE
check_ip-0.4.5.dist-info/METADATA
check_ip-0.4.5.dist-info/WHEEL
check_ip-0.4.5.dist-info/entry_points.txt
check_ip-0.4.5.dist-info/top_level.txt
check_ip-0.4.5.dist-info/RECORD
