Metadata-Version: 2.1
Name: check-ip
Version: 0.4.5
Summary: Check your public IP address and update DNS records on Cloudflare.
Home-page: https://github.com/samueljsb/check-ip/
Author: Samuel Searles-Bryant
Author-email: devel@samueljsb.co.uk
License: MIT
Platform: UNKNOWN
Requires-Dist: click
Requires-Dist: cloudflare
Requires-Dist: pyyaml
Requires-Dist: requests
